bayesline/apiclient/__init__.py
bayesline/apiclient/py.typed
bayesline/apiclient/_src/__init__.py
bayesline/apiclient/_src/apiclient.py
bayesline/apiclient/_src/client.py
bayesline/apiclient/_src/maintenance.py
bayesline/apiclient/_src/permissions.py
bayesline/apiclient/_src/settings.py
bayesline/apiclient/_src/settings_new.py
bayesline/apiclient/_src/tasks.py
bayesline/apiclient/_src/types.py
bayesline/apiclient/_src/equity/__init__.py
bayesline/apiclient/_src/equity/calendar.py
bayesline/apiclient/_src/equity/client.py
bayesline/apiclient/_src/equity/dataset.py
bayesline/apiclient/_src/equity/exposure.py
bayesline/apiclient/_src/equity/ids.py
bayesline/apiclient/_src/equity/portfolio.py
bayesline/apiclient/_src/equity/portfolio_hierarchy.py
bayesline/apiclient/_src/equity/portfolioreport.py
bayesline/apiclient/_src/equity/riskmodels.py
bayesline/apiclient/_src/equity/universe.py
bayesline/apiclient/_src/equity/upload.py
bayesline/apiclient/equity/__init__.py
bayesline_apiclient-0.11.0.dist-info/METADATA
bayesline_apiclient-0.11.0.dist-info/WHEEL
bayesline_apiclient-0.11.0.dist-info/RECORD
