Metadata-Version: 2.4
Name: bayesline-apiclient
Version: 0.11.0
Requires-Python: <4,>=3.10
Requires-Dist: bayesline-api==0.11.0
Requires-Dist: httpx<0.29,>=0.28.1
Requires-Dist: pyarrow>=16.1.0
Requires-Dist: tqdm>=4.67.1
Provides-Extra: gpu
Requires-Dist: bayesline-api[gpu]; extra == 'gpu'
